generator/__init__.py
generator/util.py
generator/version.py
test_generator-0.1.2.dist-info/top_level.txt
test_generator-0.1.2.dist-info/METADATA
test_generator-0.1.2.dist-info/DESCRIPTION.rst
test_generator-0.1.2.dist-info/metadata.json
test_generator-0.1.2.dist-info/WHEEL
test_generator-0.1.2.dist-info/RECORD
