Metadata-Version: 2.0
Name: test-generator
Version: 0.1.2
Summary: Generator is a helper for generating test methods for nose while still using unittest
Home-page: https://github.com/kevinastone/generator
Author: Kevin Stone
Author-email: kevinastone@gmail.com
License: ISCL
Keywords: generator
Platform: UNKNOWN
Classifier: Development Status :: 2 - Pre-Alpha
Classifier: Intended Audience :: Developers
Classifier: License :: OSI Approved :: ISC License (ISCL)
Classifier: Natural Language :: English
Classifier: Programming Language :: Python :: 2
Classifier: Programming Language :: Python :: 2.6
Classifier: Programming Language :: Python :: 2.7
Classifier: Programming Language :: Python :: 3
Classifier: Programming Language :: Python :: 3.3
Classifier: Programming Language :: Python :: 3.4
Requires-Dist: six
